README.md
setup.py
offlate/VERSION
offlate/__init__.py
offlate/data.json
offlate/icon.png
offlate/manager.py
offlate.egg-info/PKG-INFO
offlate.egg-info/SOURCES.txt
offlate.egg-info/dependency_links.txt
offlate.egg-info/entry_points.txt
offlate.egg-info/requires.txt
offlate.egg-info/top_level.txt
offlate/formats/__init__.py
offlate/formats/androidstrings.py
offlate/formats/appstore.py
offlate/formats/entry.py
offlate/formats/formatException.py
offlate/formats/gettext.py
offlate/formats/list.py
offlate/formats/ts.py
offlate/formats/yaml.py
offlate/locales/offlate_en.qm
offlate/locales/offlate_en.ts
offlate/locales/offlate_fr.qm
offlate/locales/offlate_fr.ts
offlate/systems/__init__.py
offlate/systems/git.py
offlate/systems/github.py
offlate/systems/gitlab.py
offlate/systems/list.py
offlate/systems/systemException.py
offlate/systems/tp.py
offlate/systems/transifex.py
offlate/ui/__init__.py
offlate/ui/about.py
offlate/ui/editor.py
offlate/ui/gitlabedit.py
offlate/ui/main.py
offlate/ui/manager.py
offlate/ui/multiplelineedit.py
offlate/ui/new.py
offlate/ui/parallel.py
offlate/ui/settings.py
offlate/ui/spellcheckedit.py
offlate/ui/tagclickedit.py